<?xml version="1.0" encoding="UTF-8" ?>
<menu-bar visible="true">
    <menu text="ファイル">
        <menu-item text="新規プロジェクトを作成" actionId="pino:create-project" />
        <menu-item text="プロジェクトを開く" actionId="pino:open-project" />
        <menu-item text="閉じる" actionId="pino:close-project" />
        <menu-item text="名前をつけて保存" actionId="pino:save-project-as" />
        <menu-item text="保存" actionId="pino:save-project" />
        <menu-item text="出力" actionId="pino:output-project" />
        <menu-item text="環境設定" actionId="pino:show-env-config" />
        <menu-item text="印刷設定" actionId="pino:show-copy-config" />
        <menu-item text="印刷" actionId="pino:copy" />
        <menu-item text="終了" actionId="pino:exit-app" />
    </menu>
    <menu text="編集">
        <menu-item text="ひとつ戻る" actionId="pino:undo" />
        <menu-item text="ひとつ進む" actionId="pino:redo" />
    </menu>
</menu-bar>